guardianlib/__init__.py
guardianlib/guardian.py
guardianlib-0.1.1.dist-info/licenses/LICENSE.txt
guardianlib-0.1.1.dist-info/METADATA
guardianlib-0.1.1.dist-info/WHEEL
guardianlib-0.1.1.dist-info/top_level.txt
guardianlib-0.1.1.dist-info/RECORD
