Metadata-Version: 2.4
Name: guardianlib
Version: 0.1.1
Summary: Python Library for FavortieGuardian
Home-page: https://github.com/ImLuni5/GuardianLib-Py
Author: ImLuni5
Requires-Python: >=3.6
License-File: LICENSE.txt
Dynamic: author
Dynamic: description
Dynamic: description-content-type
Dynamic: home-page
Dynamic: license-file
Dynamic: requires-python
Dynamic: summary
